[
    {
        "ColumnName": "title",
        "LocalizationTargetId": 600210101001,
        "Text": "Overcoming Myriad Farewells"
    },
    {
        "ColumnName": "title",
        "LocalizationTargetId": 600210101002,
        "Text": "Swordsman Starting Out"
    },
    {
        "ColumnName": "title",
        "LocalizationTargetId": 600210102001,
        "Text": "For Affection's Sake"
    },
    {
        "ColumnName": "title",
        "LocalizationTargetId": 600210102002,
        "Text": ""
    },
    {
        "ColumnName": "title",
        "LocalizationTargetId": 600210103001,
        "Text": "Knight in Brutal Armor"
    },
    {
        "ColumnName": "title",
        "LocalizationTargetId": 600210103002,
        "Text": ""
    },
    {
        "ColumnName": "title",
        "LocalizationTargetId": 600210104001,
        "Text": "Hidden Ambitions"
    },
    {
        "ColumnName": "title",
        "LocalizationTargetId": 600210104002,
        "Text": ""
    },
    {
        "ColumnName": "title",
        "LocalizationTargetId": 600210201001,
        "Text": "Fate by Fluke"
    },
    {
        "ColumnName": "title",
        "LocalizationTargetId": 600210201002,
        "Text": "In Fervor and Fearlessness"
    },
    {
        "ColumnName": "title",
        "LocalizationTargetId": 600210202001,
        "Text": "Lovely Rowdy Lass"
    },
    {
        "ColumnName": "title",
        "LocalizationTargetId": 600210202002,
        "Text": "Strong and Sweet"
    },
    {
        "ColumnName": "title",
        "LocalizationTargetId": 600210203001,
        "Text": "Headed for the Home Village"
    },
    {
        "ColumnName": "title",
        "LocalizationTargetId": 600210203002,
        "Text": "I'm the Boss!"
    },
    {
        "ColumnName": "title",
        "LocalizationTargetId": 600210206001,
        "Text": "Stealthy Shadow"
    },
    {
        "ColumnName": "title",
        "LocalizationTargetId": 600210206002,
        "Text": ""
    },
    {
        "ColumnName": "title",
        "LocalizationTargetId": 600210301001,
        "Text": "Thrilling Blade Flash"
    },
    {
        "ColumnName": "title",
        "LocalizationTargetId": 600210301002,
        "Text": "Young Soldier of Valsena"
    },
    {
        "ColumnName": "title",
        "LocalizationTargetId": 600210302001,
        "Text": "Magic Power in Bloom"
    },
    {
        "ColumnName": "title",
        "LocalizationTargetId": 600210302002,
        "Text": "Rebelling Against Fate"
    },
    {
        "ColumnName": "title",
        "LocalizationTargetId": 600210303001,
        "Text": "To Save a Friend"
    },
    {
        "ColumnName": "title",
        "LocalizationTargetId": 600210303002,
        "Text": "The Beast Within"
    },
    {
        "ColumnName": "title",
        "LocalizationTargetId": 600210304001,
        "Text": "Fifteen in the Flush of Youth"
    },
    {
        "ColumnName": "title",
        "LocalizationTargetId": 600210305001,
        "Text": "Sentiments for a Friend"
    },
    {
        "ColumnName": "title",
        "LocalizationTargetId": 600210305099,
        "Text": "Tutorial"
    },
    {
        "ColumnName": "title",
        "LocalizationTargetId": 600210306001,
        "Text": "Pride of Amazon"
    },
    {
        "ColumnName": "title",
        "LocalizationTargetId": 600210306002,
        "Text": "Search for a Brother"
    },
    {
        "ColumnName": "title",
        "LocalizationTargetId": 600210307001,
        "Text": ""
    },
    {
        "ColumnName": "title",
        "LocalizationTargetId": 600210308001,
        "Text": ""
    },
    {
        "ColumnName": "title",
        "LocalizationTargetId": 600210309001,
        "Text": "Body of Practical Study"
    },
    {
        "ColumnName": "title",
        "LocalizationTargetId": 600210309002,
        "Text": ""
    },
    {
        "ColumnName": "title",
        "LocalizationTargetId": 600210310001,
        "Text": "Flaming Dark Magic"
    },
    {
        "ColumnName": "title",
        "LocalizationTargetId": 600210401001,
        "Text": "Unwavering Friendship"
    },
    {
        "ColumnName": "title",
        "LocalizationTargetId": 600210401002,
        "Text": "Guardian's Resolve"
    },
    {
        "ColumnName": "title",
        "LocalizationTargetId": 600210402001,
        "Text": "Guided by the Great Tree"
    },
    {
        "ColumnName": "title",
        "LocalizationTargetId": 600210501001,
        "Text": "Encounter Sprung from a Seed"
    },
    {
        "ColumnName": "title",
        "LocalizationTargetId": 600210501002,
        "Text": "Weaver of Fantasies"
    },
    {
        "ColumnName": "title",
        "LocalizationTargetId": 600210502001,
        "Text": "Guided by Calling Dreams"
    },
    {
        "ColumnName": "title",
        "LocalizationTargetId": 600210502002,
        "Text": "A Sprouting Encounter"
    },
    {
        "ColumnName": "title",
        "LocalizationTargetId": 600210503001,
        "Text": "Smile for Mew!"
    },
    {
        "ColumnName": "title",
        "LocalizationTargetId": 600210504001,
        "Text": "Proud Dragoon"
    },
    {
        "ColumnName": "title",
        "LocalizationTargetId": 600210504002,
        "Text": ""
    },
    {
        "ColumnName": "title",
        "LocalizationTargetId": 600210601001,
        "Text": "Beyond the Great Calamity"
    },
    {
        "ColumnName": "title",
        "LocalizationTargetId": 600210601002,
        "Text": ""
    },
    {
        "ColumnName": "title",
        "LocalizationTargetId": 600210602001,
        "Text": "The Niccolo Vagabond"
    },
    {
        "ColumnName": "title",
        "LocalizationTargetId": 600211101001,
        "Text": ""
    },
    {
        "ColumnName": "title",
        "LocalizationTargetId": 600211102001,
        "Text": ""
    },
    {
        "ColumnName": "title",
        "LocalizationTargetId": 600211103001,
        "Text": ""
    },
    {
        "ColumnName": "title",
        "LocalizationTargetId": 600211104001,
        "Text": ""
    },
    {
        "ColumnName": "title",
        "LocalizationTargetId": 600211105001,
        "Text": ""
    },
    {
        "ColumnName": "title",
        "LocalizationTargetId": 600211106001,
        "Text": ""
    },
    {
        "ColumnName": "title",
        "LocalizationTargetId": 600211107001,
        "Text": ""
    },
    {
        "ColumnName": "title",
        "LocalizationTargetId": 600270001001,
        "Text": ""
    },
    {
        "ColumnName": "title",
        "LocalizationTargetId": 600270001002,
        "Text": ""
    },
    {
        "ColumnName": "title",
        "LocalizationTargetId": 600270001003,
        "Text": ""
    },
    {
        "ColumnName": "title",
        "LocalizationTargetId": 600270001004,
        "Text": ""
    },
    {
        "ColumnName": "title",
        "LocalizationTargetId": 600270011001,
        "Text": ""
    },
    {
        "ColumnName": "title",
        "LocalizationTargetId": 600270011002,
        "Text": ""
    },
    {
        "ColumnName": "title",
        "LocalizationTargetId": 600270011003,
        "Text": ""
    },
    {
        "ColumnName": "title",
        "LocalizationTargetId": 600270011004,
        "Text": ""
    },
    {
        "ColumnName": "title",
        "LocalizationTargetId": 600270011005,
        "Text": ""
    },
    {
        "ColumnName": "title",
        "LocalizationTargetId": 600270012001,
        "Text": ""
    },
    {
        "ColumnName": "title",
        "LocalizationTargetId": 600270012002,
        "Text": ""
    },
    {
        "ColumnName": "title",
        "LocalizationTargetId": 600270012003,
        "Text": ""
    },
    {
        "ColumnName": "title",
        "LocalizationTargetId": 600270012004,
        "Text": ""
    },
    {
        "ColumnName": "title",
        "LocalizationTargetId": 600270012005,
        "Text": ""
    },
    {
        "ColumnName": "title",
        "LocalizationTargetId": 600270013001,
        "Text": ""
    },
    {
        "ColumnName": "title",
        "LocalizationTargetId": 600270013002,
        "Text": ""
    },
    {
        "ColumnName": "title",
        "LocalizationTargetId": 600270013003,
        "Text": ""
    },
    {
        "ColumnName": "title",
        "LocalizationTargetId": 600270013004,
        "Text": ""
    },
    {
        "ColumnName": "title",
        "LocalizationTargetId": 600270013005,
        "Text": ""
    },
    {
        "ColumnName": "title",
        "LocalizationTargetId": 600270014001,
        "Text": ""
    },
    {
        "ColumnName": "title",
        "LocalizationTargetId": 600270014002,
        "Text": ""
    },
    {
        "ColumnName": "title",
        "LocalizationTargetId": 600270014003,
        "Text": ""
    },
    {
        "ColumnName": "title",
        "LocalizationTargetId": 600270014004,
        "Text": ""
    },
    {
        "ColumnName": "title",
        "LocalizationTargetId": 600270014005,
        "Text": ""
    },
    {
        "ColumnName": "title",
        "LocalizationTargetId": 600270015001,
        "Text": ""
    },
    {
        "ColumnName": "title",
        "LocalizationTargetId": 600270015002,
        "Text": ""
    },
    {
        "ColumnName": "title",
        "LocalizationTargetId": 600270015003,
        "Text": ""
    },
    {
        "ColumnName": "title",
        "LocalizationTargetId": 600270015004,
        "Text": ""
    },
    {
        "ColumnName": "title",
        "LocalizationTargetId": 600270015005,
        "Text": ""
    },
    {
        "ColumnName": "title",
        "LocalizationTargetId": 600270016001,
        "Text": ""
    },
    {
        "ColumnName": "title",
        "LocalizationTargetId": 600270016002,
        "Text": ""
    },
    {
        "ColumnName": "title",
        "LocalizationTargetId": 600270016003,
        "Text": ""
    },
    {
        "ColumnName": "title",
        "LocalizationTargetId": 600270016004,
        "Text": ""
    },
    {
        "ColumnName": "title",
        "LocalizationTargetId": 600270016005,
        "Text": ""
    },
    {
        "ColumnName": "title",
        "LocalizationTargetId": 600270017001,
        "Text": ""
    },
    {
        "ColumnName": "title",
        "LocalizationTargetId": 600270017002,
        "Text": ""
    },
    {
        "ColumnName": "title",
        "LocalizationTargetId": 600270017003,
        "Text": ""
    },
    {
        "ColumnName": "title",
        "LocalizationTargetId": 600270017004,
        "Text": ""
    },
    {
        "ColumnName": "title",
        "LocalizationTargetId": 600270017005,
        "Text": ""
    },
    {
        "ColumnName": "title",
        "LocalizationTargetId": 600270018001,
        "Text": ""
    },
    {
        "ColumnName": "title",
        "LocalizationTargetId": 600270018002,
        "Text": ""
    },
    {
        "ColumnName": "title",
        "LocalizationTargetId": 600270018003,
        "Text": ""
    },
    {
        "ColumnName": "title",
        "LocalizationTargetId": 600270018004,
        "Text": ""
    },
    {
        "ColumnName": "title",
        "LocalizationTargetId": 600270018005,
        "Text": ""
    },
    {
        "ColumnName": "title",
        "LocalizationTargetId": 600270019001,
        "Text": ""
    },
    {
        "ColumnName": "title",
        "LocalizationTargetId": 600270019002,
        "Text": ""
    },
    {
        "ColumnName": "title",
        "LocalizationTargetId": 600270019003,
        "Text": ""
    },
    {
        "ColumnName": "title",
        "LocalizationTargetId": 600270019004,
        "Text": ""
    },
    {
        "ColumnName": "title",
        "LocalizationTargetId": 600270019005,
        "Text": ""
    },
    {
        "ColumnName": "title",
        "LocalizationTargetId": 600270019006,
        "Text": ""
    },
    {
        "ColumnName": "title",
        "LocalizationTargetId": 600270019007,
        "Text": ""
    }
]