[
    {
        "ColumnNameoffset": "name",
        "LocalizationTargetId": 40100000000000,
        "Textoffset": "No Effect"
    },
    {
        "ColumnNameoffset": "name",
        "LocalizationTargetId": 40100000000101,
        "Textoffset": "Candy"
    },
    {
        "ColumnNameoffset": "name",
        "LocalizationTargetId": 40100000000102,
        "Textoffset": "Chocolate"
    },
    {
        "ColumnNameoffset": "name",
        "LocalizationTargetId": 40100000000103,
        "Textoffset": "Honey Elixir"
    },
    {
        "ColumnNameoffset": "name",
        "LocalizationTargetId": 40100000000110,
        "Textoffset": "Faerie Walnut"
    },
    {
        "ColumnNameoffset": "name",
        "LocalizationTargetId": 40100000000120,
        "Textoffset": "Medical Herb"
    },
    {
        "ColumnNameoffset": "name",
        "LocalizationTargetId": 40100000001001,
        "Textoffset": "Poisoned"
    },
    {
        "ColumnNameoffset": "name",
        "LocalizationTargetId": 40100000001002,
        "Textoffset": "Slowed"
    },
    {
        "ColumnNameoffset": "name",
        "LocalizationTargetId": 40100000001003,
        "Textoffset": "Asleep"
    },
    {
        "ColumnNameoffset": "name",
        "LocalizationTargetId": 40100000001004,
        "Textoffset": "Stunned"
    },
    {
        "ColumnNameoffset": "name",
        "LocalizationTargetId": 40100000001005,
        "Textoffset": "Dazed"
    },
    {
        "ColumnNameoffset": "name",
        "LocalizationTargetId": 40100000001006,
        "Textoffset": "Poisoned"
    },
    {
        "ColumnNameoffset": "name",
        "LocalizationTargetId": 40100000001007,
        "Textoffset": "Asleep"
    },
    {
        "ColumnNameoffset": "name",
        "LocalizationTargetId": 40100000002000,
        "Textoffset": "[ALL FOES] Restores HP: 30% of parameters"
    },
    {
        "ColumnNameoffset": "name",
        "LocalizationTargetId": 40100000002001,
        "Textoffset": "[ALL FOES] Restores HP: 50% of parameters"
    },
    {
        "ColumnNameoffset": "name",
        "LocalizationTargetId": 40100000003000,
        "Textoffset": "[SINGLE FOE] CON: +10% SPR: +10% (15s)"
    },
    {
        "ColumnNameoffset": "name",
        "LocalizationTargetId": 40100000003001,
        "Textoffset": "[SINGLE FOE] CON: +25% SPR: +25% (10s)"
    },
    {
        "ColumnNameoffset": "name",
        "LocalizationTargetId": 40100000004001,
        "Textoffset": "[SINGLE FOE] CON: -25%SPR: -25% (10s)"
    },
    {
        "ColumnNameoffset": "name",
        "LocalizationTargetId": 40100000005001,
        "Textoffset": "30 MP DMG"
    },
    {
        "ColumnNameoffset": "name",
        "LocalizationTargetId": 40100000010000,
        "Textoffset": "[PLAYER] Boost STR/INT SLv. 1"
    },
    {
        "ColumnNameoffset": "name",
        "LocalizationTargetId": 40100000010001,
        "Textoffset": "[PLAYER] Boost STR/INT SLv. 2"
    },
    {
        "ColumnNameoffset": "name",
        "LocalizationTargetId": 40100000010002,
        "Textoffset": "[PLAYER] Boost STR/INT SLv. 3"
    },
    {
        "ColumnNameoffset": "name",
        "LocalizationTargetId": 40100000020020,
        "Textoffset": "STR Boost (2\u2606) SLv. 1"
    },
    {
        "ColumnNameoffset": "name",
        "LocalizationTargetId": 40100000020021,
        "Textoffset": "STR Boost (2\u2606) SLv. 2"
    },
    {
        "ColumnNameoffset": "name",
        "LocalizationTargetId": 40100000020022,
        "Textoffset": "STR Boost (2\u2606) SLv. 3"
    },
    {
        "ColumnNameoffset": "name",
        "LocalizationTargetId": 40100000020030,
        "Textoffset": "STR Boost (3\u2606) SLv. 1"
    },
    {
        "ColumnNameoffset": "name",
        "LocalizationTargetId": 40100000020031,
        "Textoffset": "STR Boost (3\u2606) SLv. 2"
    },
    {
        "ColumnNameoffset": "name",
        "LocalizationTargetId": 40100000020032,
        "Textoffset": "STR Boost (3\u2606) SLv. 3"
    },
    {
        "ColumnNameoffset": "name",
        "LocalizationTargetId": 40100000020040,
        "Textoffset": "STR Boost (4\u2606) SLv. 1"
    },
    {
        "ColumnNameoffset": "name",
        "LocalizationTargetId": 40100000020041,
        "Textoffset": "STR Boost (4\u2606) SLv. 2"
    },
    {
        "ColumnNameoffset": "name",
        "LocalizationTargetId": 40100000020042,
        "Textoffset": "STR Boost (4\u2606) SLv. 3"
    },
    {
        "ColumnNameoffset": "name",
        "LocalizationTargetId": 40100000030020,
        "Textoffset": "INT Boost (2\u2606) SLv. 1"
    },
    {
        "ColumnNameoffset": "name",
        "LocalizationTargetId": 40100000030021,
        "Textoffset": "INT Boost (2\u2606) SLv. 2"
    },
    {
        "ColumnNameoffset": "name",
        "LocalizationTargetId": 40100000030022,
        "Textoffset": "INT Boost (2\u2606) SLv. 3"
    },
    {
        "ColumnNameoffset": "name",
        "LocalizationTargetId": 40100000030030,
        "Textoffset": "INT Boost (3\u2606) SLv. 1"
    },
    {
        "ColumnNameoffset": "name",
        "LocalizationTargetId": 40100000030031,
        "Textoffset": "INT Boost (3\u2606) SLv. 2"
    },
    {
        "ColumnNameoffset": "name",
        "LocalizationTargetId": 40100000030032,
        "Textoffset": "INT Boost (3\u2606) SLv. 3"
    },
    {
        "ColumnNameoffset": "name",
        "LocalizationTargetId": 40100000030040,
        "Textoffset": "INT Boost (4\u2606) SLv. 1"
    },
    {
        "ColumnNameoffset": "name",
        "LocalizationTargetId": 40100000030041,
        "Textoffset": "INT Boost (4\u2606) SLv. 2"
    },
    {
        "ColumnNameoffset": "name",
        "LocalizationTargetId": 40100000030042,
        "Textoffset": "INT Boost (4\u2606) SLv. 3"
    },
    {
        "ColumnNameoffset": "name",
        "LocalizationTargetId": 40100000040001,
        "Textoffset": "l10n_efficacy_group_error"
    },
    {
        "ColumnNameoffset": "name",
        "LocalizationTargetId": 40100000040002,
        "Textoffset": "l10n_efficacy_group_error"
    },
    {
        "ColumnNameoffset": "name",
        "LocalizationTargetId": 40100000040003,
        "Textoffset": "l10n_efficacy_group_error"
    },
    {
        "ColumnNameoffset": "name",
        "LocalizationTargetId": 40100000040011,
        "Textoffset": "l10n_efficacy_group_error"
    },
    {
        "ColumnNameoffset": "name",
        "LocalizationTargetId": 40100000040012,
        "Textoffset": "l10n_efficacy_group_error"
    },
    {
        "ColumnNameoffset": "name",
        "LocalizationTargetId": 40100000040013,
        "Textoffset": "l10n_efficacy_group_error"
    },
    {
        "ColumnNameoffset": "name",
        "LocalizationTargetId": 40100000070000,
        "Textoffset": "[SELF] STR: +20% (Continuous) Group1/Slot1"
    },
    {
        "ColumnNameoffset": "name",
        "LocalizationTargetId": 40100000090000,
        "Textoffset": "For Flails"
    },
    {
        "ColumnNameoffset": "name",
        "LocalizationTargetId": 40100000090010,
        "Textoffset": "For Flails"
    },
    {
        "ColumnNameoffset": "name",
        "LocalizationTargetId": 40100001000011,
        "Textoffset": "Cure target's status ailments (All)"
    },
    {
        "ColumnNameoffset": "name",
        "LocalizationTargetId": 40100001000101,
        "Textoffset": "The Tale Begins"
    },
    {
        "ColumnNameoffset": "name",
        "LocalizationTargetId": 40100001000111,
        "Textoffset": "The Tale Begins"
    },
    {
        "ColumnNameoffset": "name",
        "LocalizationTargetId": 40100001000121,
        "Textoffset": "The Tale Begins"
    },
    {
        "ColumnNameoffset": "name",
        "LocalizationTargetId": 40100001000131,
        "Textoffset": "The Tale Begins"
    },
    {
        "ColumnNameoffset": "name",
        "LocalizationTargetId": 40100001000141,
        "Textoffset": "The Tale Begins"
    },
    {
        "ColumnNameoffset": "name",
        "LocalizationTargetId": 40100001000201,
        "Textoffset": "Seekers of Mana"
    },
    {
        "ColumnNameoffset": "name",
        "LocalizationTargetId": 40100001000211,
        "Textoffset": "Seekers of Mana"
    },
    {
        "ColumnNameoffset": "name",
        "LocalizationTargetId": 40100001000221,
        "Textoffset": "Seekers of Mana"
    },
    {
        "ColumnNameoffset": "name",
        "LocalizationTargetId": 40100001000231,
        "Textoffset": "Seekers of Mana"
    },
    {
        "ColumnNameoffset": "name",
        "LocalizationTargetId": 40100001000241,
        "Textoffset": "Seekers of Mana"
    },
    {
        "ColumnNameoffset": "name",
        "LocalizationTargetId": 40100001000301,
        "Textoffset": "Cibba"
    },
    {
        "ColumnNameoffset": "name",
        "LocalizationTargetId": 40100001000311,
        "Textoffset": "Cibba"
    },
    {
        "ColumnNameoffset": "name",
        "LocalizationTargetId": 40100001000321,
        "Textoffset": "Cibba"
    },
    {
        "ColumnNameoffset": "name",
        "LocalizationTargetId": 40100001000331,
        "Textoffset": "Cibba"
    },
    {
        "ColumnNameoffset": "name",
        "LocalizationTargetId": 40100001000341,
        "Textoffset": "Cibba"
    },
    {
        "ColumnNameoffset": "name",
        "LocalizationTargetId": 40100001000401,
        "Textoffset": "Freak Show and Tell"
    },
    {
        "ColumnNameoffset": "name",
        "LocalizationTargetId": 40100001000411,
        "Textoffset": "Freak Show and Tell"
    },
    {
        "ColumnNameoffset": "name",
        "LocalizationTargetId": 40100001000421,
        "Textoffset": "Freak Show and Tell"
    },
    {
        "ColumnNameoffset": "name",
        "LocalizationTargetId": 40100001000431,
        "Textoffset": "Freak Show and Tell"
    },
    {
        "ColumnNameoffset": "name",
        "LocalizationTargetId": 40100001000441,
        "Textoffset": "Freak Show and Tell"
    },
    {
        "ColumnNameoffset": "name",
        "LocalizationTargetId": 40100001000501,
        "Textoffset": "I won't hear it!"
    },
    {
        "ColumnNameoffset": "name",
        "LocalizationTargetId": 40100001000511,
        "Textoffset": "I won't hear it!"
    },
    {
        "ColumnNameoffset": "name",
        "LocalizationTargetId": 40100001000521,
        "Textoffset": "I won't hear it!"
    },
    {
        "ColumnNameoffset": "name",
        "LocalizationTargetId": 40100001000531,
        "Textoffset": "I won't hear it!"
    },
    {
        "ColumnNameoffset": "name",
        "LocalizationTargetId": 40100001000541,
        "Textoffset": "I won't hear it!"
    },
    {
        "ColumnNameoffset": "name",
        "LocalizationTargetId": 40100002000101,
        "Textoffset": "White Dragon Child"
    },
    {
        "ColumnNameoffset": "name",
        "LocalizationTargetId": 40100002000111,
        "Textoffset": "White Dragon Child"
    },
    {
        "ColumnNameoffset": "name",
        "LocalizationTargetId": 40100002000121,
        "Textoffset": "White Dragon Child"
    },
    {
        "ColumnNameoffset": "name",
        "LocalizationTargetId": 40100002000131,
        "Textoffset": "White Dragon Child"
    },
    {
        "ColumnNameoffset": "name",
        "LocalizationTargetId": 40100002000141,
        "Textoffset": "White Dragon Child"
    },
    {
        "ColumnNameoffset": "name",
        "LocalizationTargetId": 40100002000201,
        "Textoffset": "A Heated Situation"
    },
    {
        "ColumnNameoffset": "name",
        "LocalizationTargetId": 40100002000211,
        "Textoffset": "A Heated Situation"
    },
    {
        "ColumnNameoffset": "name",
        "LocalizationTargetId": 40100002000221,
        "Textoffset": "A Heated Situation"
    },
    {
        "ColumnNameoffset": "name",
        "LocalizationTargetId": 40100002000231,
        "Textoffset": "A Heated Situation"
    },
    {
        "ColumnNameoffset": "name",
        "LocalizationTargetId": 40100002000241,
        "Textoffset": "A Heated Situation"
    },
    {
        "ColumnNameoffset": "name",
        "LocalizationTargetId": 40100002000301,
        "Textoffset": "Pity Peddlers"
    },
    {
        "ColumnNameoffset": "name",
        "LocalizationTargetId": 40100002000311,
        "Textoffset": "Pity Peddlers"
    },
    {
        "ColumnNameoffset": "name",
        "LocalizationTargetId": 40100002000321,
        "Textoffset": "Pity Peddlers"
    },
    {
        "ColumnNameoffset": "name",
        "LocalizationTargetId": 40100002000331,
        "Textoffset": "Pity Peddlers"
    },
    {
        "ColumnNameoffset": "name",
        "LocalizationTargetId": 40100002000341,
        "Textoffset": "Pity Peddlers"
    },
    {
        "ColumnNameoffset": "name",
        "LocalizationTargetId": 40100002000401,
        "Textoffset": "Hi-yo Mech Rider! Away!"
    },
    {
        "ColumnNameoffset": "name",
        "LocalizationTargetId": 40100002000411,
        "Textoffset": "Hi-yo Mech Rider! Away!"
    },
    {
        "ColumnNameoffset": "name",
        "LocalizationTargetId": 40100002000421,
        "Textoffset": "Hi-yo Mech Rider! Away!"
    },
    {
        "ColumnNameoffset": "name",
        "LocalizationTargetId": 40100002000431,
        "Textoffset": "Hi-yo Mech Rider! Away!"
    },
    {
        "ColumnNameoffset": "name",
        "LocalizationTargetId": 40100002000441,
        "Textoffset": "Hi-yo Mech Rider! Away!"
    },
    {
        "ColumnNameoffset": "name",
        "LocalizationTargetId": 40100002000501,
        "Textoffset": "Pamaela"
    },
    {
        "ColumnNameoffset": "name",
        "LocalizationTargetId": 40100002000511,
        "Textoffset": "Pamaela"
    },
    {
        "ColumnNameoffset": "name",
        "LocalizationTargetId": 40100002000521,
        "Textoffset": "Pamaela"
    },
    {
        "ColumnNameoffset": "name",
        "LocalizationTargetId": 40100002000531,
        "Textoffset": "Pamaela"
    },
    {
        "ColumnNameoffset": "name",
        "LocalizationTargetId": 40100002000541,
        "Textoffset": "Pamaela"
    },
    {
        "ColumnNameoffset": "name",
        "LocalizationTargetId": 40100002000601,
        "Textoffset": "The Chosen One"
    },
    {
        "ColumnNameoffset": "name",
        "LocalizationTargetId": 40100002000611,
        "Textoffset": "The Chosen One"
    },
    {
        "ColumnNameoffset": "name",
        "LocalizationTargetId": 40100002000621,
        "Textoffset": "The Chosen One"
    },
    {
        "ColumnNameoffset": "name",
        "LocalizationTargetId": 40100002000631,
        "Textoffset": "The Chosen One"
    },
    {
        "ColumnNameoffset": "name",
        "LocalizationTargetId": 40100002000641,
        "Textoffset": "The Chosen One"
    },
    {
        "ColumnNameoffset": "name",
        "LocalizationTargetId": 40100002000701,
        "Textoffset": "Resonating Sword and Seed"
    },
    {
        "ColumnNameoffset": "name",
        "LocalizationTargetId": 40100002000711,
        "Textoffset": "Resonating Sword and Seed"
    },
    {
        "ColumnNameoffset": "name",
        "LocalizationTargetId": 40100002000721,
        "Textoffset": "Resonating Sword and Seed"
    },
    {
        "ColumnNameoffset": "name",
        "LocalizationTargetId": 40100002000731,
        "Textoffset": "Resonating Sword and Seed"
    },
    {
        "ColumnNameoffset": "name",
        "LocalizationTargetId": 40100002000741,
        "Textoffset": "Resonating Sword and Seed"
    },
    {
        "ColumnNameoffset": "name",
        "LocalizationTargetId": 40100002000801,
        "Textoffset": "Big Bad Werewolves"
    },
    {
        "ColumnNameoffset": "name",
        "LocalizationTargetId": 40100002000811,
        "Textoffset": "Big Bad Werewolves"
    },
    {
        "ColumnNameoffset": "name",
        "LocalizationTargetId": 40100002000821,
        "Textoffset": "Big Bad Werewolves"
    },
    {
        "ColumnNameoffset": "name",
        "LocalizationTargetId": 40100002000831,
        "Textoffset": "Big Bad Werewolves"
    },
    {
        "ColumnNameoffset": "name",
        "LocalizationTargetId": 40100002000841,
        "Textoffset": "Big Bad Werewolves"
    },
    {
        "ColumnNameoffset": "name",
        "LocalizationTargetId": 40100002100011,
        "Textoffset": "[TARGET] Restore HP: 60% of restore power"
    },
    {
        "ColumnNameoffset": "name",
        "LocalizationTargetId": 40100002100012,
        "Textoffset": "[TARGET] Restore HP: 80% of restore power"
    },
    {
        "ColumnNameoffset": "name",
        "LocalizationTargetId": 40100002100021,
        "Textoffset": "[TARGET] Restore HP: 80% of restore power"
    },
    {
        "ColumnNameoffset": "name",
        "LocalizationTargetId": 40100002100022,
        "Textoffset": "[TARGET] Restore HP: 100% of restore power"
    },
    {
        "ColumnNameoffset": "name",
        "LocalizationTargetId": 40100002100031,
        "Textoffset": "[TARGET] Restore HP: 100% of restore power"
    },
    {
        "ColumnNameoffset": "name",
        "LocalizationTargetId": 40100002100032,
        "Textoffset": "[TARGET] Restore HP: 120% of restore power"
    },
    {
        "ColumnNameoffset": "name",
        "LocalizationTargetId": 40100003000101,
        "Textoffset": "Machine Golem Shuffle"
    },
    {
        "ColumnNameoffset": "name",
        "LocalizationTargetId": 40100003000111,
        "Textoffset": "Machine Golem Shuffle"
    },
    {
        "ColumnNameoffset": "name",
        "LocalizationTargetId": 40100003000121,
        "Textoffset": "Machine Golem Shuffle"
    },
    {
        "ColumnNameoffset": "name",
        "LocalizationTargetId": 40100003000131,
        "Textoffset": "Machine Golem Shuffle"
    },
    {
        "ColumnNameoffset": "name",
        "LocalizationTargetId": 40100003000141,
        "Textoffset": "Machine Golem Shuffle"
    },
    {
        "ColumnNameoffset": "name",
        "LocalizationTargetId": 40100003000201,
        "Textoffset": "Vuscav's Great Escape"
    },
    {
        "ColumnNameoffset": "name",
        "LocalizationTargetId": 40100003000211,
        "Textoffset": "Vuscav's Great Escape"
    },
    {
        "ColumnNameoffset": "name",
        "LocalizationTargetId": 40100003000221,
        "Textoffset": "Vuscav's Great Escape"
    },
    {
        "ColumnNameoffset": "name",
        "LocalizationTargetId": 40100003000231,
        "Textoffset": "Vuscav's Great Escape"
    },
    {
        "ColumnNameoffset": "name",
        "LocalizationTargetId": 40100003000241,
        "Textoffset": "Vuscav's Great Escape"
    },
    {
        "ColumnNameoffset": "name",
        "LocalizationTargetId": 40100003000301,
        "Textoffset": "Von Boyage"
    },
    {
        "ColumnNameoffset": "name",
        "LocalizationTargetId": 40100003000311,
        "Textoffset": "Von Boyage"
    },
    {
        "ColumnNameoffset": "name",
        "LocalizationTargetId": 40100003000321,
        "Textoffset": "Von Boyage"
    },
    {
        "ColumnNameoffset": "name",
        "LocalizationTargetId": 40100003000331,
        "Textoffset": "Von Boyage"
    },
    {
        "ColumnNameoffset": "name",
        "LocalizationTargetId": 40100003000341,
        "Textoffset": "Von Boyage"
    },
    {
        "ColumnNameoffset": "name",
        "LocalizationTargetId": 40100003000401,
        "Textoffset": "The Wind in Our Sails"
    },
    {
        "ColumnNameoffset": "name",
        "LocalizationTargetId": 40100003000411,
        "Textoffset": "The Wind in Our Sails"
    },
    {
        "ColumnNameoffset": "name",
        "LocalizationTargetId": 40100003000421,
        "Textoffset": "The Wind in Our Sails"
    },
    {
        "ColumnNameoffset": "name",
        "LocalizationTargetId": 40100003000431,
        "Textoffset": "The Wind in Our Sails"
    },
    {
        "ColumnNameoffset": "name",
        "LocalizationTargetId": 40100003000441,
        "Textoffset": "The Wind in Our Sails"
    },
    {
        "ColumnNameoffset": "name",
        "LocalizationTargetId": 40100003000501,
        "Textoffset": "All I have left"
    },
    {
        "ColumnNameoffset": "name",
        "LocalizationTargetId": 40100003000511,
        "Textoffset": "All I have left"
    },
    {
        "ColumnNameoffset": "name",
        "LocalizationTargetId": 40100003000521,
        "Textoffset": "All I have left"
    },
    {
        "ColumnNameoffset": "name",
        "LocalizationTargetId": 40100003000531,
        "Textoffset": "All I have left"
    },
    {
        "ColumnNameoffset": "name",
        "LocalizationTargetId": 40100003000541,
        "Textoffset": "All I have left"
    },
    {
        "ColumnNameoffset": "name",
        "LocalizationTargetId": 40100003000601,
        "Textoffset": "A Reawwy Big Jump"
    },
    {
        "ColumnNameoffset": "name",
        "LocalizationTargetId": 40100003000611,
        "Textoffset": "A Reawwy Big Jump"
    },
    {
        "ColumnNameoffset": "name",
        "LocalizationTargetId": 40100003000621,
        "Textoffset": "A Reawwy Big Jump"
    },
    {
        "ColumnNameoffset": "name",
        "LocalizationTargetId": 40100003000631,
        "Textoffset": "A Reawwy Big Jump"
    },
    {
        "ColumnNameoffset": "name",
        "LocalizationTargetId": 40100003000641,
        "Textoffset": "A Reawwy Big Jump"
    },
    {
        "ColumnNameoffset": "name",
        "LocalizationTargetId": 40100003000701,
        "Textoffset": "A Bitter Farewell"
    },
    {
        "ColumnNameoffset": "name",
        "LocalizationTargetId": 40100003000711,
        "Textoffset": "A Bitter Farewell"
    },
    {
        "ColumnNameoffset": "name",
        "LocalizationTargetId": 40100003000721,
        "Textoffset": "A Bitter Farewell"
    },
    {
        "ColumnNameoffset": "name",
        "LocalizationTargetId": 40100003000731,
        "Textoffset": "A Bitter Farewell"
    },
    {
        "ColumnNameoffset": "name",
        "LocalizationTargetId": 40100003000741,
        "Textoffset": "A Bitter Farewell"
    },
    {
        "ColumnNameoffset": "name",
        "LocalizationTargetId": 40100003000801,
        "Textoffset": "Run for It"
    },
    {
        "ColumnNameoffset": "name",
        "LocalizationTargetId": 40100003000811,
        "Textoffset": "Run for It"
    },
    {
        "ColumnNameoffset": "name",
        "LocalizationTargetId": 40100003000821,
        "Textoffset": "Run for It"
    },
    {
        "ColumnNameoffset": "name",
        "LocalizationTargetId": 40100003000831,
        "Textoffset": "Run for It"
    },
    {
        "ColumnNameoffset": "name",
        "LocalizationTargetId": 40100003000841,
        "Textoffset": "Run for It"
    },
    {
        "ColumnNameoffset": "name",
        "LocalizationTargetId": 40100003030011,
        "Textoffset": "[SELF] STR: +5% (60s)"
    },
    {
        "ColumnNameoffset": "name",
        "LocalizationTargetId": 40100003030012,
        "Textoffset": "[SELF] STR: +15% (60s)"
    },
    {
        "ColumnNameoffset": "name",
        "LocalizationTargetId": 40100003030021,
        "Textoffset": "[SELF] STR: +10% (60s)"
    },
    {
        "ColumnNameoffset": "name",
        "LocalizationTargetId": 40100003030022,
        "Textoffset": "[SELF] STR: +20% (60s)"
    },
    {
        "ColumnNameoffset": "name",
        "LocalizationTargetId": 40100003030031,
        "Textoffset": "[SELF] STR: +15% (60s)"
    },
    {
        "ColumnNameoffset": "name",
        "LocalizationTargetId": 40100003030032,
        "Textoffset": "[SELF] STR: +25% (60s)"
    },
    {
        "ColumnNameoffset": "name",
        "LocalizationTargetId": 40100003040011,
        "Textoffset": "[SELF] CON: +15% (60s)"
    },
    {
        "ColumnNameoffset": "name",
        "LocalizationTargetId": 40100003040012,
        "Textoffset": "[SELF] CON: +25% (60s)"
    },
    {
        "ColumnNameoffset": "name",
        "LocalizationTargetId": 40100003040021,
        "Textoffset": "[SELF] CON: +20% (60s)"
    },
    {
        "ColumnNameoffset": "name",
        "LocalizationTargetId": 40100003040022,
        "Textoffset": "[SELF] CON: +30% (60s)"
    },
    {
        "ColumnNameoffset": "name",
        "LocalizationTargetId": 40100003040031,
        "Textoffset": "[SELF] CON: +25% (60s)"
    },
    {
        "ColumnNameoffset": "name",
        "LocalizationTargetId": 40100003040032,
        "Textoffset": "[SELF] CON: +35% (60s)"
    },
    {
        "ColumnNameoffset": "name",
        "LocalizationTargetId": 40100003050011,
        "Textoffset": "[SELF] INT: +5% (60s)"
    },
    {
        "ColumnNameoffset": "name",
        "LocalizationTargetId": 40100003050012,
        "Textoffset": "[SELF] INT: +15% (60s)"
    },
    {
        "ColumnNameoffset": "name",
        "LocalizationTargetId": 40100003050021,
        "Textoffset": "[SELF] INT: +10% (60s)"
    },
    {
        "ColumnNameoffset": "name",
        "LocalizationTargetId": 40100003050022,
        "Textoffset": "[SELF] INT: +20% (60s)"
    },
    {
        "ColumnNameoffset": "name",
        "LocalizationTargetId": 40100003050031,
        "Textoffset": "[SELF] INT: +15% (60s)"
    },
    {
        "ColumnNameoffset": "name",
        "LocalizationTargetId": 40100003050032,
        "Textoffset": "[SELF] INT: +25% (60s)"
    },
    {
        "ColumnNameoffset": "name",
        "LocalizationTargetId": 40100003060011,
        "Textoffset": "[SELF] SPR: +15% (60s)"
    },
    {
        "ColumnNameoffset": "name",
        "LocalizationTargetId": 40100003060012,
        "Textoffset": "[SELF] SPR: +25% (60s)"
    },
    {
        "ColumnNameoffset": "name",
        "LocalizationTargetId": 40100003060021,
        "Textoffset": "[SELF] SPR: +20% (60s)"
    },
    {
        "ColumnNameoffset": "name",
        "LocalizationTargetId": 40100003060022,
        "Textoffset": "[SELF] SPR: +30% (60s)"
    },
    {
        "ColumnNameoffset": "name",
        "LocalizationTargetId": 40100003060031,
        "Textoffset": "[SELF] SPR: +25% (60s)"
    },
    {
        "ColumnNameoffset": "name",
        "LocalizationTargetId": 40100003060032,
        "Textoffset": "[SELF] SPR: +35% (60s)"
    },
    {
        "ColumnNameoffset": "name",
        "LocalizationTargetId": 40100003070011,
        "Textoffset": "[SELF] LCK: +30 (60s)"
    },
    {
        "ColumnNameoffset": "name",
        "LocalizationTargetId": 40100003070012,
        "Textoffset": "[SELF] LCK: +50 (60s)"
    },
    {
        "ColumnNameoffset": "name",
        "LocalizationTargetId": 40100003070021,
        "Textoffset": "[SELF] LCK: +50 (60s)"
    },
    {
        "ColumnNameoffset": "name",
        "LocalizationTargetId": 40100003070022,
        "Textoffset": "[SELF] LCK: +70 (60s)"
    },
    {
        "ColumnNameoffset": "name",
        "LocalizationTargetId": 40100003070031,
        "Textoffset": "[SELF] LCK: +70 (60s)"
    },
    {
        "ColumnNameoffset": "name",
        "LocalizationTargetId": 40100003070032,
        "Textoffset": "[SELF] LCK: +90 (60s)"
    },
    {
        "ColumnNameoffset": "name",
        "LocalizationTargetId": 40100004000101,
        "Textoffset": "A Curious Creeping Whip"
    },
    {
        "ColumnNameoffset": "name",
        "LocalizationTargetId": 40100004000111,
        "Textoffset": "A Curious Creeping Whip"
    },
    {
        "ColumnNameoffset": "name",
        "LocalizationTargetId": 40100004000121,
        "Textoffset": "A Curious Creeping Whip"
    },
    {
        "ColumnNameoffset": "name",
        "LocalizationTargetId": 40100004000131,
        "Textoffset": "A Curious Creeping Whip"
    },
    {
        "ColumnNameoffset": "name",
        "LocalizationTargetId": 40100004000141,
        "Textoffset": "A Curious Creeping Whip"
    },
    {
        "ColumnNameoffset": "name",
        "LocalizationTargetId": 40100004000201,
        "Textoffset": "Village Elder"
    },
    {
        "ColumnNameoffset": "name",
        "LocalizationTargetId": 40100004000211,
        "Textoffset": "Village Elder"
    },
    {
        "ColumnNameoffset": "name",
        "LocalizationTargetId": 40100004000221,
        "Textoffset": "Village Elder"
    },
    {
        "ColumnNameoffset": "name",
        "LocalizationTargetId": 40100004000231,
        "Textoffset": "Village Elder"
    },
    {
        "ColumnNameoffset": "name",
        "LocalizationTargetId": 40100004000241,
        "Textoffset": "Village Elder"
    },
    {
        "ColumnNameoffset": "name",
        "LocalizationTargetId": 40100004000301,
        "Textoffset": "Buju Breakout"
    },
    {
        "ColumnNameoffset": "name",
        "LocalizationTargetId": 40100004000311,
        "Textoffset": "Buju Breakout"
    },
    {
        "ColumnNameoffset": "name",
        "LocalizationTargetId": 40100004000321,
        "Textoffset": "Buju Breakout"
    },
    {
        "ColumnNameoffset": "name",
        "LocalizationTargetId": 40100004000331,
        "Textoffset": "Buju Breakout"
    },
    {
        "ColumnNameoffset": "name",
        "LocalizationTargetId": 40100004000341,
        "Textoffset": "Buju Breakout"
    },
    {
        "ColumnNameoffset": "name",
        "LocalizationTargetId": 40100004000401,
        "Textoffset": "Little Spirit Faye"
    },
    {
        "ColumnNameoffset": "name",
        "LocalizationTargetId": 40100004000411,
        "Textoffset": "Little Spirit Faye"
    },
    {
        "ColumnNameoffset": "name",
        "LocalizationTargetId": 40100004000421,
        "Textoffset": "Little Spirit Faye"
    },
    {
        "ColumnNameoffset": "name",
        "LocalizationTargetId": 40100004000431,
        "Textoffset": "Little Spirit Faye"
    },
    {
        "ColumnNameoffset": "name",
        "LocalizationTargetId": 40100004000441,
        "Textoffset": "Little Spirit Faye"
    },
    {
        "ColumnNameoffset": "name",
        "LocalizationTargetId": 40100004130011,
        "Textoffset": "[TARGET] STR: -20% (25s)"
    },
    {
        "ColumnNameoffset": "name",
        "LocalizationTargetId": 40100004130012,
        "Textoffset": "[TARGET] STR: -30% (25s)"
    },
    {
        "ColumnNameoffset": "name",
        "LocalizationTargetId": 40100004130021,
        "Textoffset": "[TARGET] STR: -30% (25s)"
    },
    {
        "ColumnNameoffset": "name",
        "LocalizationTargetId": 40100004130022,
        "Textoffset": "[TARGET] STR: -40% (25s)"
    },
    {
        "ColumnNameoffset": "name",
        "LocalizationTargetId": 40100004130031,
        "Textoffset": "[TARGET] STR: -40% (25s)"
    },
    {
        "ColumnNameoffset": "name",
        "LocalizationTargetId": 40100004130032,
        "Textoffset": "[TARGET] STR: -50% (25s)"
    },
    {
        "ColumnNameoffset": "name",
        "LocalizationTargetId": 40100004140011,
        "Textoffset": "[TARGET] CON: -15% (25s)"
    },
    {
        "ColumnNameoffset": "name",
        "LocalizationTargetId": 40100004140012,
        "Textoffset": "[TARGET] CON: -25% (25s)"
    },
    {
        "ColumnNameoffset": "name",
        "LocalizationTargetId": 40100004140021,
        "Textoffset": "[TARGET] CON: -25% (25s)"
    },
    {
        "ColumnNameoffset": "name",
        "LocalizationTargetId": 40100004140022,
        "Textoffset": "[TARGET] CON: -35% (25s)"
    },
    {
        "ColumnNameoffset": "name",
        "LocalizationTargetId": 40100004140031,
        "Textoffset": "[TARGET] CON: -35% (25s)"
    },
    {
        "ColumnNameoffset": "name",
        "LocalizationTargetId": 40100004140032,
        "Textoffset": "[TARGET] CON: -45% (25s)"
    },
    {
        "ColumnNameoffset": "name",
        "LocalizationTargetId": 40100004150011,
        "Textoffset": "[TARGET] INT: -20% (25s)"
    },
    {
        "ColumnNameoffset": "name",
        "LocalizationTargetId": 40100004150012,
        "Textoffset": "[TARGET] INT: -30% (25s)"
    },
    {
        "ColumnNameoffset": "name",
        "LocalizationTargetId": 40100004150021,
        "Textoffset": "[TARGET] INT: -30% (25s)"
    },
    {
        "ColumnNameoffset": "name",
        "LocalizationTargetId": 40100004150022,
        "Textoffset": "[TARGET] INT: -40% (25s)"
    },
    {
        "ColumnNameoffset": "name",
        "LocalizationTargetId": 40100004150031,
        "Textoffset": "[TARGET] INT: -40% (25s)"
    },
    {
        "ColumnNameoffset": "name",
        "LocalizationTargetId": 40100004150032,
        "Textoffset": "[TARGET] INT: -50% (25s)"
    },
    {
        "ColumnNameoffset": "name",
        "LocalizationTargetId": 40100004160011,
        "Textoffset": "[TARGET] SPR: -15% (25s)"
    },
    {
        "ColumnNameoffset": "name",
        "LocalizationTargetId": 40100004160012,
        "Textoffset": "[TARGET] SPR: -25% (25s)"
    },
    {
        "ColumnNameoffset": "name",
        "LocalizationTargetId": 40100004160021,
        "Textoffset": "[TARGET] SPR: -25% (25s)"
    },
    {
        "ColumnNameoffset": "name",
        "LocalizationTargetId": 40100004160022,
        "Textoffset": "[TARGET] SPR: -35% (25s)"
    },
    {
        "ColumnNameoffset": "name",
        "LocalizationTargetId": 40100004160031,
        "Textoffset": "[TARGET] SPR: -35% (25s)"
    },
    {
        "ColumnNameoffset": "name",
        "LocalizationTargetId": 40100004160032,
        "Textoffset": "[TARGET] SPR: -45% (25s)"
    },
    {
        "ColumnNameoffset": "name",
        "LocalizationTargetId": 40100005000101,
        "Textoffset": "Rulers of the World"
    },
    {
        "ColumnNameoffset": "name",
        "LocalizationTargetId": 40100005000111,
        "Textoffset": "Rulers of the World"
    },
    {
        "ColumnNameoffset": "name",
        "LocalizationTargetId": 40100005000121,
        "Textoffset": "Rulers of the World"
    },
    {
        "ColumnNameoffset": "name",
        "LocalizationTargetId": 40100005000131,
        "Textoffset": "Rulers of the World"
    },
    {
        "ColumnNameoffset": "name",
        "LocalizationTargetId": 40100005000141,
        "Textoffset": "Rulers of the World"
    },
    {
        "ColumnNameoffset": "name",
        "LocalizationTargetId": 40100005000201,
        "Textoffset": "It's the Li'l Things"
    },
    {
        "ColumnNameoffset": "name",
        "LocalizationTargetId": 40100005000211,
        "Textoffset": "It's the Li'l Things"
    },
    {
        "ColumnNameoffset": "name",
        "LocalizationTargetId": 40100005000221,
        "Textoffset": "It's the Li'l Things"
    },
    {
        "ColumnNameoffset": "name",
        "LocalizationTargetId": 40100005000231,
        "Textoffset": "It's the Li'l Things"
    },
    {
        "ColumnNameoffset": "name",
        "LocalizationTargetId": 40100005000241,
        "Textoffset": "It's the Li'l Things"
    },
    {
        "ColumnNameoffset": "name",
        "LocalizationTargetId": 40100005000301,
        "Textoffset": "Masterful Merchant"
    },
    {
        "ColumnNameoffset": "name",
        "LocalizationTargetId": 40100005000311,
        "Textoffset": "Masterful Merchant"
    },
    {
        "ColumnNameoffset": "name",
        "LocalizationTargetId": 40100005000321,
        "Textoffset": "Masterful Merchant"
    },
    {
        "ColumnNameoffset": "name",
        "LocalizationTargetId": 40100005000331,
        "Textoffset": "Masterful Merchant"
    },
    {
        "ColumnNameoffset": "name",
        "LocalizationTargetId": 40100005000341,
        "Textoffset": "Masterful Merchant"
    },
    {
        "ColumnNameoffset": "name",
        "LocalizationTargetId": 40100005000401,
        "Textoffset": "Pelican"
    },
    {
        "ColumnNameoffset": "name",
        "LocalizationTargetId": 40100005000411,
        "Textoffset": "Pelican"
    },
    {
        "ColumnNameoffset": "name",
        "LocalizationTargetId": 40100005000421,
        "Textoffset": "Pelican"
    },
    {
        "ColumnNameoffset": "name",
        "LocalizationTargetId": 40100005000431,
        "Textoffset": "Pelican"
    },
    {
        "ColumnNameoffset": "name",
        "LocalizationTargetId": 40100005000441,
        "Textoffset": "Pelican"
    },
    {
        "ColumnNameoffset": "name",
        "LocalizationTargetId": 40100005000501,
        "Textoffset": "Tree Chat"
    },
    {
        "ColumnNameoffset": "name",
        "LocalizationTargetId": 40100005000511,
        "Textoffset": "Tree Chat"
    },
    {
        "ColumnNameoffset": "name",
        "LocalizationTargetId": 40100005000521,
        "Textoffset": "Tree Chat"
    },
    {
        "ColumnNameoffset": "name",
        "LocalizationTargetId": 40100005000531,
        "Textoffset": "Tree Chat"
    },
    {
        "ColumnNameoffset": "name",
        "LocalizationTargetId": 40100005000541,
        "Textoffset": "Tree Chat"
    },
    {
        "ColumnNameoffset": "name",
        "LocalizationTargetId": 40100005040001,
        "Textoffset": "[SELF] Gain SA (45s)/CON: +10% (45s)"
    },
    {
        "ColumnNameoffset": "name",
        "LocalizationTargetId": 40100005040002,
        "Textoffset": "[SELF] Gain SA (45s)/CON: +20% (45s)"
    },
    {
        "ColumnNameoffset": "name",
        "LocalizationTargetId": 40100005040011,
        "Textoffset": "[SELF] Gain SA (45s)/CON: +15% (45s)"
    },
    {
        "ColumnNameoffset": "name",
        "LocalizationTargetId": 40100005040012,
        "Textoffset": "[SELF] Gain SA (45s)/CON: +25% (45s)"
    },
    {
        "ColumnNameoffset": "name",
        "LocalizationTargetId": 40100005040021,
        "Textoffset": "[SELF] Gain SA (50s)/CON: +15% (50s)"
    },
    {
        "ColumnNameoffset": "name",
        "LocalizationTargetId": 40100005040022,
        "Textoffset": "[SELF] Gain SA (50s)/CON: +25% (50s)"
    },
    {
        "ColumnNameoffset": "name",
        "LocalizationTargetId": 40100005040031,
        "Textoffset": "[SELF] Gain SA (60s)/CON: +15% (60s)"
    },
    {
        "ColumnNameoffset": "name",
        "LocalizationTargetId": 40100005040032,
        "Textoffset": "[SELF] Gain SA (60s)/CON: +25% (60s)"
    },
    {
        "ColumnNameoffset": "name",
        "LocalizationTargetId": 40100005040041,
        "Textoffset": "[SELF] Gain SA (60s)/CON: +15% (60s)"
    },
    {
        "ColumnNameoffset": "name",
        "LocalizationTargetId": 40100005040042,
        "Textoffset": "[SELF] Gain SA (60s)/CON: +25% (60s)"
    },
    {
        "ColumnNameoffset": "name",
        "LocalizationTargetId": 40100006000101,
        "Textoffset": "Xangar, the Living Flame"
    },
    {
        "ColumnNameoffset": "name",
        "LocalizationTargetId": 40100006000111,
        "Textoffset": "Xangar, the Living Flame"
    },
    {
        "ColumnNameoffset": "name",
        "LocalizationTargetId": 40100006000121,
        "Textoffset": "Xangar, the Living Flame"
    },
    {
        "ColumnNameoffset": "name",
        "LocalizationTargetId": 40100006000131,
        "Textoffset": "Xangar, the Living Flame"
    },
    {
        "ColumnNameoffset": "name",
        "LocalizationTargetId": 40100006000141,
        "Textoffset": "Xangar, the Living Flame"
    },
    {
        "ColumnNameoffset": "name",
        "LocalizationTargetId": 40100006000201,
        "Textoffset": "The Swooping Sword"
    },
    {
        "ColumnNameoffset": "name",
        "LocalizationTargetId": 40100006000211,
        "Textoffset": "The Swooping Sword"
    },
    {
        "ColumnNameoffset": "name",
        "LocalizationTargetId": 40100006000221,
        "Textoffset": "The Swooping Sword"
    },
    {
        "ColumnNameoffset": "name",
        "LocalizationTargetId": 40100006000231,
        "Textoffset": "The Swooping Sword"
    },
    {
        "ColumnNameoffset": "name",
        "LocalizationTargetId": 40100006000241,
        "Textoffset": "The Swooping Sword"
    },
    {
        "ColumnNameoffset": "name",
        "LocalizationTargetId": 40100006000301,
        "Textoffset": "Seamoon"
    },
    {
        "ColumnNameoffset": "name",
        "LocalizationTargetId": 40100006000311,
        "Textoffset": "Seamoon"
    },
    {
        "ColumnNameoffset": "name",
        "LocalizationTargetId": 40100006000321,
        "Textoffset": "Seamoon"
    },
    {
        "ColumnNameoffset": "name",
        "LocalizationTargetId": 40100006000331,
        "Textoffset": "Seamoon"
    },
    {
        "ColumnNameoffset": "name",
        "LocalizationTargetId": 40100006000341,
        "Textoffset": "Seamoon"
    },
    {
        "ColumnNameoffset": "name",
        "LocalizationTargetId": 40100006000401,
        "Textoffset": "A Branch Bestowed"
    },
    {
        "ColumnNameoffset": "name",
        "LocalizationTargetId": 40100006000411,
        "Textoffset": "A Branch Bestowed"
    },
    {
        "ColumnNameoffset": "name",
        "LocalizationTargetId": 40100006000421,
        "Textoffset": "A Branch Bestowed"
    },
    {
        "ColumnNameoffset": "name",
        "LocalizationTargetId": 40100006000431,
        "Textoffset": "A Branch Bestowed"
    },
    {
        "ColumnNameoffset": "name",
        "LocalizationTargetId": 40100006000441,
        "Textoffset": "A Branch Bestowed"
    },
    {
        "ColumnNameoffset": "name",
        "LocalizationTargetId": 40100006000501,
        "Textoffset": "Best Quest for Your Buck"
    },
    {
        "ColumnNameoffset": "name",
        "LocalizationTargetId": 40100006000511,
        "Textoffset": "Best Quest for Your Buck"
    },
    {
        "ColumnNameoffset": "name",
        "LocalizationTargetId": 40100006000521,
        "Textoffset": "Best Quest for Your Buck"
    },
    {
        "ColumnNameoffset": "name",
        "LocalizationTargetId": 40100006000531,
        "Textoffset": "Best Quest for Your Buck"
    },
    {
        "ColumnNameoffset": "name",
        "LocalizationTargetId": 40100006000541,
        "Textoffset": "Best Quest for Your Buck"
    },
    {
        "ColumnNameoffset": "name",
        "LocalizationTargetId": 40100011000101,
        "Textoffset": "Set Off for Adventure"
    },
    {
        "ColumnNameoffset": "name",
        "LocalizationTargetId": 40100011000111,
        "Textoffset": "Set Off for Adventure"
    },
    {
        "ColumnNameoffset": "name",
        "LocalizationTargetId": 40100011000121,
        "Textoffset": "Set Off for Adventure"
    },
    {
        "ColumnNameoffset": "name",
        "LocalizationTargetId": 40100011000131,
        "Textoffset": "Set Off for Adventure"
    },
    {
        "ColumnNameoffset": "name",
        "LocalizationTargetId": 40100011000141,
        "Textoffset": "Set Off for Adventure"
    },
    {
        "ColumnNameoffset": "name",
        "LocalizationTargetId": 40100011000201,
        "Textoffset": "Who Bears the Sword"
    },
    {
        "ColumnNameoffset": "name",
        "LocalizationTargetId": 40100011000211,
        "Textoffset": "Who Bears the Sword"
    },
    {
        "ColumnNameoffset": "name",
        "LocalizationTargetId": 40100011000221,
        "Textoffset": "Who Bears the Sword"
    },
    {
        "ColumnNameoffset": "name",
        "LocalizationTargetId": 40100011000231,
        "Textoffset": "Who Bears the Sword"
    },
    {
        "ColumnNameoffset": "name",
        "LocalizationTargetId": 40100011000241,
        "Textoffset": "Who Bears the Sword"
    },
    {
        "ColumnNameoffset": "name",
        "LocalizationTargetId": 40100011000301,
        "Textoffset": "A Branch Bestowed"
    },
    {
        "ColumnNameoffset": "name",
        "LocalizationTargetId": 40100011000311,
        "Textoffset": "A Branch Bestowed"
    },
    {
        "ColumnNameoffset": "name",
        "LocalizationTargetId": 40100011000321,
        "Textoffset": "A Branch Bestowed"
    },
    {
        "ColumnNameoffset": "name",
        "LocalizationTargetId": 40100011000331,
        "Textoffset": "A Branch Bestowed"
    },
    {
        "ColumnNameoffset": "name",
        "LocalizationTargetId": 40100011000341,
        "Textoffset": "A Branch Bestowed"
    },
    {
        "ColumnNameoffset": "name",
        "LocalizationTargetId": 40100011000401,
        "Textoffset": "Shadow on Soaring Wings"
    },
    {
        "ColumnNameoffset": "name",
        "LocalizationTargetId": 40100011000411,
        "Textoffset": "Shadow on Soaring Wings"
    },
    {
        "ColumnNameoffset": "name",
        "LocalizationTargetId": 40100011000421,
        "Textoffset": "Shadow on Soaring Wings"
    },
    {
        "ColumnNameoffset": "name",
        "LocalizationTargetId": 40100011000431,
        "Textoffset": "Shadow on Soaring Wings"
    },
    {
        "ColumnNameoffset": "name",
        "LocalizationTargetId": 40100011000441,
        "Textoffset": "Shadow on Soaring Wings"
    },
    {
        "ColumnNameoffset": "name",
        "LocalizationTargetId": 40100011000501,
        "Textoffset": "Briarborough Faerie Boss"
    },
    {
        "ColumnNameoffset": "name",
        "LocalizationTargetId": 40100011000511,
        "Textoffset": "Briarborough Faerie Boss"
    },
    {
        "ColumnNameoffset": "name",
        "LocalizationTargetId": 40100011000521,
        "Textoffset": "Briarborough Faerie Boss"
    },
    {
        "ColumnNameoffset": "name",
        "LocalizationTargetId": 40100011000531,
        "Textoffset": "Briarborough Faerie Boss"
    },
    {
        "ColumnNameoffset": "name",
        "LocalizationTargetId": 40100011000541,
        "Textoffset": "Briarborough Faerie Boss"
    },
    {
        "ColumnNameoffset": "name",
        "LocalizationTargetId": 40100011100101,
        "Textoffset": "The Tower on High"
    },
    {
        "ColumnNameoffset": "name",
        "LocalizationTargetId": 40100011100111,
        "Textoffset": "The Tower on High"
    },
    {
        "ColumnNameoffset": "name",
        "LocalizationTargetId": 40100011100121,
        "Textoffset": "The Tower on High"
    },
    {
        "ColumnNameoffset": "name",
        "LocalizationTargetId": 40100011100131,
        "Textoffset": "The Tower on High"
    },
    {
        "ColumnNameoffset": "name",
        "LocalizationTargetId": 40100011100141,
        "Textoffset": "The Tower on High"
    },
    {
        "ColumnNameoffset": "name",
        "LocalizationTargetId": 40100011100301,
        "Textoffset": "Victory High Five"
    },
    {
        "ColumnNameoffset": "name",
        "LocalizationTargetId": 40100011100311,
        "Textoffset": "Victory High Five"
    },
    {
        "ColumnNameoffset": "name",
        "LocalizationTargetId": 40100011100321,
        "Textoffset": "Victory High Five"
    },
    {
        "ColumnNameoffset": "name",
        "LocalizationTargetId": 40100011100331,
        "Textoffset": "Victory High Five"
    },
    {
        "ColumnNameoffset": "name",
        "LocalizationTargetId": 40100011100341,
        "Textoffset": "Victory High Five"
    },
    {
        "ColumnNameoffset": "name",
        "LocalizationTargetId": 40100507800104,
        "Textoffset": "Mantis Ant (\u771f\u7a7a\u6d3e)"
    },
    {
        "ColumnNameoffset": "name",
        "LocalizationTargetId": 40100507800106,
        "Textoffset": "Ep2 Boss Mantis Ant Use"
    },
    {
        "ColumnNameoffset": "name",
        "LocalizationTargetId": 40100507900101,
        "Textoffset": "Raxa Poison (Basic)"
    },
    {
        "ColumnNameoffset": "name",
        "LocalizationTargetId": 40100507900102,
        "Textoffset": "Raxa Poison (Magic Release)"
    },
    {
        "ColumnNameoffset": "name",
        "LocalizationTargetId": 40100507900401,
        "Textoffset": "(Raxa Use) Poison (202205 Rank Event)"
    },
    {
        "ColumnNameoffset": "name",
        "LocalizationTargetId": 40100508100105,
        "Textoffset": "Ep4 Boss Hugger Use"
    },
    {
        "ColumnNameoffset": "name",
        "LocalizationTargetId": 40100508100107,
        "Textoffset": "Ep4 Boss Hugger Use"
    },
    {
        "ColumnNameoffset": "name",
        "LocalizationTargetId": 40100508200104,
        "Textoffset": "For Ep5 Warrior Faerie Use"
    },
    {
        "ColumnNameoffset": "name",
        "LocalizationTargetId": 40100508200108,
        "Textoffset": "For Ep5 Warrior Faerie Use"
    },
    {
        "ColumnNameoffset": "name",
        "LocalizationTargetId": 40100508200109,
        "Textoffset": "For Ep5 Warrior Faerie Use"
    },
    {
        "ColumnNameoffset": "name",
        "LocalizationTargetId": 40100508600104,
        "Textoffset": "Co-op Event Use"
    },
    {
        "ColumnNameoffset": "name",
        "LocalizationTargetId": 40100508600107,
        "Textoffset": "Co-op Event Use"
    },
    {
        "ColumnNameoffset": "name",
        "LocalizationTargetId": 40100508600109,
        "Textoffset": "Co-op Event Use"
    },
    {
        "ColumnNameoffset": "name",
        "LocalizationTargetId": 40110203001021,
        "Textoffset": "[SELF] INT: +10% (60s)/SPR: +20% (60s)"
    },
    {
        "ColumnNameoffset": "name",
        "LocalizationTargetId": 40110203001022,
        "Textoffset": "[SELF] INT: +20% (60s)/SPR: +20% (60s)"
    },
    {
        "ColumnNameoffset": "name",
        "LocalizationTargetId": 40110303001031,
        "Textoffset": "[SELF] STR: +5% (15s)/When HP 30% or lower, STR: +25% (15s)"
    },
    {
        "ColumnNameoffset": "name",
        "LocalizationTargetId": 40110303001032,
        "Textoffset": "[SELF] STR: +5% (15s)/When HP 30% or lower, STR: +25% (15s)"
    },
    {
        "ColumnNameoffset": "name",
        "LocalizationTargetId": 40110303001033,
        "Textoffset": "[SELF] STR: +5% (15s)/When HP 30% or lower, STR: +25% (15s)"
    },
    {
        "ColumnNameoffset": "name",
        "LocalizationTargetId": 40110310001021,
        "Textoffset": "[SELF] INT: +20% (60s)/CON: -40% (60s) (Debuff)"
    },
    {
        "ColumnNameoffset": "name",
        "LocalizationTargetId": 40110310001022,
        "Textoffset": "[SELF] INT: +40% (60s)/CON: -40% (60s) (Debuff)"
    },
    {
        "ColumnNameoffset": "name",
        "LocalizationTargetId": 40111101001041,
        "Textoffset": "ST Bonus Effect (Continuous HP Recovery)"
    },
    {
        "ColumnNameoffset": "name",
        "LocalizationTargetId": 40111101001042,
        "Textoffset": "ST Bonus Effect (Continuous HP Recovery)"
    },
    {
        "ColumnNameoffset": "name",
        "LocalizationTargetId": 40111102001041,
        "Textoffset": "ST Bonus Effect (Continuous HP Recovery)"
    },
    {
        "ColumnNameoffset": "name",
        "LocalizationTargetId": 40111102001042,
        "Textoffset": "ST Bonus Effect (Continuous HP Recovery)"
    },
    {
        "ColumnNameoffset": "name",
        "LocalizationTargetId": 40111104001011,
        "Textoffset": "M.ATK/50% chance to daze (Foe ineffective)"
    },
    {
        "ColumnNameoffset": "name",
        "LocalizationTargetId": 40111104001021,
        "Textoffset": "[AOE] Restore HP (10s/RCV: 10%/Every 1s)"
    },
    {
        "ColumnNameoffset": "name",
        "LocalizationTargetId": 40111104001031,
        "Textoffset": "[TARGET] Cure status ailments (Poison/Sleep)"
    },
    {
        "ColumnNameoffset": "name",
        "LocalizationTargetId": 40111106001041,
        "Textoffset": "ST Bonus Effect (Poison)"
    },
    {
        "ColumnNameoffset": "name",
        "LocalizationTargetId": 40111107001021,
        "Textoffset": "[TARGET] Cure status ailments (Slow/Stun)"
    },
    {
        "ColumnNameoffset": "name",
        "LocalizationTargetId": 40111107001041,
        "Textoffset": "[PARTY] Restore HP: 50% of restore power"
    },
    {
        "ColumnNameoffset": "name",
        "LocalizationTargetId": 40111107001042,
        "Textoffset": "[PARTY] Restore HP: 70% of restore power"
    }
]